[
	{
		"__TYPE__": "SharedSliceContent",
		"variation": "default",
		"primary": {
			"heading": {
				"__TYPE__": "FieldContent",
				"value": "cowboy",
				"type": "Text"
			}
		},
		"items": [
			{
				"__TYPE__": "GroupItemContent",
				"value": [
					[
						"title",
						{
							"__TYPE__": "FieldContent",
							"value": "straw",
							"type": "Text"
						}
					],
					[
						"time_period",
						{
							"__TYPE__": "FieldContent",
							"value": "indeed",
							"type": "Text"
						}
					],
					[
						"institution",
						{
							"__TYPE__": "FieldContent",
							"value": "type",
							"type": "Text"
						}
					],
					[
						"description",
						{
							"__TYPE__": "StructuredTextContent",
							"value": [
								{
									"type": "paragraph",
									"content": {
										"text": "Aute sint non esse eiusmod occaecat tempor. Non irure deserunt Lorem cillum deserunt cupidatat laborum reprehenderit eiusmod."
									}
								}
							]
						}
					]
				]
			}
		]
	}
]